lintkit-1.1.1.dist-info/METADATA
lintkit-1.1.1.dist-info/WHEEL
lintkit-1.1.1.dist-info/entry_points.txt
lintkit/__init__.py
lintkit/_ignore.py
lintkit/_run.py
lintkit/_value.py
lintkit/available.py
lintkit/check.py
lintkit/cli/__init__.py
lintkit/cli/_main.py
lintkit/cli/_parser.py
lintkit/cli/_subcommand.py
lintkit/error.py
lintkit/loader.py
lintkit/output.py
lintkit/py.typed
lintkit/py.typed.license
lintkit/registry.py
lintkit/rule.py
lintkit/settings.py
lintkit/type_definitions.py
lintkit-1.1.1.dist-info/RECORD
