Metadata-Version: 2.4
Name: lintkit
Version: 1.1.1
Summary: Build your own linter in minutes - from Python code to config files (YAML, JSON, TOML)
Author: open-nudge
Maintainer: open-nudge
License-Expression: Apache-2.0
Classifier: Development Status :: 2 - Pre-Alpha
Classifier: Intended Audience :: Developers
Classifier: Programming Language :: Python
Classifier: Programming Language :: Python :: 3 :: Only
Classifier: Programming Language :: Python :: 3.12
Classifier: Programming Language :: Python :: 3.13
Classifier: Programming Language :: Python :: 3.14
Classifier: Topic :: Software Development :: Libraries
Classifier: Topic :: Software Development :: Libraries :: Python Modules
Classifier: Typing :: Typed
Project-URL: Changelog, https://github.com/open-nudge/lintkit/blob/master/CHANGELOG.md
Project-URL: Documentation, https://open-nudge.github.io/lintkit
Project-URL: Homepage, https://open-nudge.github.io/lintkit
Project-URL: Issues, https://github.com/open-nudge/lintkit/issues
Project-URL: Repository, https://github.com/open-nudge/lintkit
Requires-Python: >=3.12
Requires-Dist: wrapt>=1
Provides-Extra: rich
Requires-Dist: rich>=13; extra == "rich"
Provides-Extra: toml
Requires-Dist: tomlkit>=0.13.3; extra == "toml"
Provides-Extra: yaml
Requires-Dist: ruamel.yaml>=0.18.14; extra == "yaml"
Provides-Extra: output
Requires-Dist: lintkit[rich]; extra == "output"
Provides-Extra: all
Requires-Dist: lintkit[output]; extra == "all"
Requires-Dist: lintkit[yaml]; extra == "all"
Requires-Dist: lintkit[toml]; extra == "all"
